mkdocs_ipymd/__init__.py
mkdocs_ipymd/cli/main.py
mkdocs_ipymd/converters/__init__.py
mkdocs_ipymd/converters/base.py
mkdocs_ipymd/converters/templates/default_template.tpl
mkdocs_ipymd/converters/to_jupyter.py
mkdocs_ipymd/converters/to_markdown.py
mkdocs_ipymd/plugin.py
mkdocs_ipymd-0.0.4.dist-info/METADATA
mkdocs_ipymd-0.0.4.dist-info/WHEEL
mkdocs_ipymd-0.0.4.dist-info/entry_points.txt
mkdocs_ipymd-0.0.4.dist-info/RECORD
